setup.py
bugger/__init__.py
bugger/console.py
bugger.egg-info/PKG-INFO
bugger.egg-info/SOURCES.txt
bugger.egg-info/dependency_links.txt
bugger.egg-info/top_level.txt
bugger/tests/__init__.py
bugger/tests/test_console.py