Metadata-Version: 1.0
Name: bugger
Version: 0.2
Summary: Easily embed accessible python interactive console into your application
Home-page: http://github.com/posborne/bugger
Author: Paul Osborne
Author-email: osbpau@gmail.com
License: MIT
Keywords: bugger interactive InteractiveConsole interpreter console code InteractiveInterpreter
Platform: UNKNOWN
